<?xml version="1.0" ?>
<review>
  <source value="http://www.buscape.com.br/avaliacao--celular-com-bastante-funcoes-mas-para-uso-moderado---smartphone-samsung-wave-533-gt-s5330-desbloqueado--466147.html"/>
  <evaluation_date value="29/07/2013"/>
  <category value="Celular e Smartphone"/>
  <product value="Celular e Smartphone Smartphone Samsung Wave 533 GT-S5330 Desbloqueado"/>
  <stars value="3.0"/>
  <recommends value="Yes"/>
  <user value="29605"/>
  <thumbsUp value="0"/>
  <thumbsDown value="0"/>
  <pros>Duração da Bateria
Design
Durabilidade
Display
Câmera
multimidia
</pros>
  <cons>Custo-Benefício
Sistema Operacional
</cons>
  <opinion>Celular de boa duraçao com boa interaçao multimidia mas que deixa a desejar pelo sistema operacional que é lento e nao oferece o que foi prometido,facil de usar tem recursos bons a bateria dura muito e é muito resistente e bonito.</opinion>
</review>
