<?xml version="1.0" ?>
<review>
  <source value="http://www.buscape.com.br/avaliacao--simples-e-funcional--celular-nokia-6030-desbloqueado--13056.html"/>
  <evaluation_date value="29/07/2006"/>
  <category value="Celular e Smartphone"/>
  <product value="Celular e Smartphone Celular Nokia 6030 Desbloqueado"/>
  <stars value="4.0"/>
  <recommends value="Yes"/>
  <user value="24928"/>
  <thumbsUp value="1"/>
  <thumbsDown value="0"/>
  <pros>Duração da Bateria
Design
Custo-Benefício
Facilidade de Uso
Funções e Características
Display
Operadora
</pros>
  <cons>Durabilidade
</cons>
  <opinion>Comprei este celular motivado por problemas de recepção de meu antigo aparelho (Nokia 6180 - Vivo) no novo local de trabalho . Não fazia questão de câmera fotográfica , mas queria como alternativa o rádio para ouvir durante minhas caminhadas . Além da facilidade de uso já característica dos aparelhos da Nokia , surpreendeu-me a autonomia da bateria , que dura de 10 a 14 dias sem recarga (contra 4 do anterior) . Também achei a recepção mais &quot;limpa&quot; , sem tanto chiado ou aquela voz mais &quot;metálica&quot;. O rádio FM funciona melhor do que em alguns MP3 player que tive oportunidade de testar . Somados aos recursos de despertador , calendário , acesso a internet , tudo em um bonito display por um preço razoável , estou muito satisfeito com o celular .

O que gostei: Autonomia da bateria , recepção do radio , display colorido

O que não gostei: Aparente fragilidade</opinion>
</review>
