<?xml version="1.0" ?>
<review>
  <source value="http://www.buscape.com.br/avaliacao--moderno---celular-motorola-w220-desbloqueado--21349.html"/>
  <evaluation_date value="03/12/2007"/>
  <category value="Celular e Smartphone"/>
  <product value="Celular e Smartphone Celular Motorola W220 Desbloqueado"/>
  <stars value="4.0"/>
  <recommends value="Yes"/>
  <user value="28415"/>
  <thumbsUp value="1"/>
  <thumbsDown value="0"/>
  <pros>Duração da Bateria
Design
Custo-Benefício
Facilidade de Uso
Funções e Características
Durabilidade
Display
Operadora
</pros>
  <cons>Não possui nenhum ponto negativo.
</cons>
  <opinion>Pesquisei muito para comprar este celular. Achei muito prático. Para quem não liga de tantas frecuras como câmera, mp3, bluetooth e outras este é uma boa pedida. Além do custo-benefício!

O que gostei: Moderno, prático, sem frecuras e os ícones são um charme!

O que não gostei: Não tem confirmação de recebimento de mensagem e as teclas são um pouco duras.</opinion>
</review>
