<?xml version="1.0" ?>
<review>
  <source value="http://www.buscape.com.br/avaliacao--insatisfeito--celular-huawei-g2800s-desbloqueado--341171.html"/>
  <evaluation_date value="02/08/2012"/>
  <category value="Celular e Smartphone"/>
  <product value="Celular e Smartphone Celular Huawei G2800S Desbloqueado"/>
  <stars value="3.0"/>
  <recommends value=""/>
  <user value="23033"/>
  <thumbsUp value="1"/>
  <thumbsDown value="0"/>
  <pros>Duração da Bateria
Facilidade de Uso
Operadora
</pros>
  <cons>Design
Custo-Benefício
Funções e Características
Durabilidade
Display
Câmera
</cons>
  <opinion>Nao vale apena comprar, tem produtos melhores no mercado.

O que gostei: Barato, rapido para fazer as coisas, facil de usar, alto, leve e pequeno.

O que não gostei: propaganda enganosa, pois nao possui memoria interna - possui apenas espaco para 5 msg - nao tem como mudar a cor da letra na tela principal... pois esse letra tem uma cor ruim.</opinion>
</review>
