<?xml version="1.0" ?>
<review>
  <source value="http://www.buscape.com.br/avaliacao--serve-pra-ligar-mas-o-acesso-a-internet-e-muito-fraco---celular-samsung-star-3-duos-gt-s5222-desbloqueado--479802.html"/>
  <evaluation_date value="18/09/2013"/>
  <category value="Celular e Smartphone"/>
  <product value="Celular e Smartphone Celular Samsung Star 3 Duos GT-S5222 Desbloqueado"/>
  <stars value="2.0"/>
  <recommends value=""/>
  <user value="1824"/>
  <thumbsUp value="0"/>
  <thumbsDown value="0"/>
  <pros>Design
Facilidade de Uso
Câmera
</pros>
  <cons>Duração da Bateria
Custo-Benefício
Funções e Características
aplicativos
Navegação
</cons>
  <opinion>muito frustante, não baixa os aplicativos e nenhum é compatível também, acesso às redes muito limitada, não abre nem o site da samsung inteira pra registrar o produto.</opinion>
</review>
