<?xml version="1.0" ?>
<review>
  <source value="http://www.buscape.com.br/avaliacao--ja-nasceu-defasado---smartphone-nokia-x6-16gb-desbloqueado--181218.html"/>
  <evaluation_date value="29/03/2011"/>
  <category value="Celular e Smartphone"/>
  <product value="Celular e Smartphone Smartphone Nokia X6 16GB Desbloqueado"/>
  <stars value="2.0"/>
  <recommends value=""/>
  <user value="9125"/>
  <thumbsUp value="2"/>
  <thumbsDown value="0"/>
  <pros>Duração da Bateria
Design
Câmera
</pros>
  <cons>Custo-Benefício
Facilidade de Uso
Funções e Características
Durabilidade
Display
Operadora
</cons>
  <opinion>Como meu primeiro smartphone não fiquei satisfeito. Esperava mais de um produto Nokia. Acho que esse sistema operacional é que deve estar muito defasado. Os aplicativos são fraquíssimos e incomparáveis com aparelhos mais avançados como o Iphone. Tenho e não recomendo. Você muitas vezes tem que insistir teclando algum atalho até que ele resolva acionar (em tempo: sem ter nada carregado na memória). Comprei com a opção de downloads ilimitados de música. Pelo menos isso valeu a pena...

O que gostei: Tela de boa qualidade, boa resolução, bem sensível ao toque. Bonito. Excelente filmagem e fotos (para um celular, claro). Áudio bom.

O que não gostei: Reinicia sozinho do nada, sem mais nem menos. As vezes desliga sozinho. Os menus são muito confusos. Processador muito lento.</opinion>
</review>
