<?xml version="1.0" ?>
<review>
  <source value="http://www.buscape.com.br/avaliacao--otiimo--celular-vaic-c5000-desbloqueado--189860.html"/>
  <evaluation_date value="23/04/2011"/>
  <category value="Celular e Smartphone"/>
  <product value="Celular e Smartphone Celular Vaic C5000 Desbloqueado"/>
  <stars value="1.0"/>
  <recommends value="Yes"/>
  <user value="17059"/>
  <thumbsUp value="0"/>
  <thumbsDown value="0"/>
  <pros>Design
Operadora
</pros>
  <cons>Duração da Bateria
Custo-Benefício
Facilidade de Uso
Funções e Características
Durabilidade
Display
Câmera
</cons>
  <opinion>muuito booun , goostei muuito mesmo , podeem contra a voontade . naum vaao se arrepeebdeer !

O que gostei: celulaar peerfeeito maanolo !

O que não gostei: nadaa</opinion>
</review>
