<?xml version="1.0" ?>
<review>
  <source value="http://www.buscape.com.br/avaliacao--nao-recomendo--celular-motorola-i296-nextel--229853.html"/>
  <evaluation_date value="03/08/2011"/>
  <category value="Celular e Smartphone"/>
  <product value="Celular e Smartphone Celular Motorola i296 Nextel"/>
  <stars value="2.0"/>
  <recommends value=""/>
  <user value="8438"/>
  <thumbsUp value="0"/>
  <thumbsDown value="0"/>
  <pros>Design
Facilidade de Uso
Durabilidade
Display
Operadora
</pros>
  <cons>Duração da Bateria
Custo-Benefício
Funções e Características
Câmera
</cons>
  <opinion>Esse como os outros aparelhos da Motorola é péssimo&quot; É uma pena a Nextel não trabalhar com Nokia

O que gostei: Nada

O que não gostei: Péssimo aparelho, conheço cerca de 10 pessoas com este aparelho, as baterias duram no máximo 2 dias, o software é muito lento, vive travando e algumas funções do meu não funcionam mais, tenho ele a cerca de 4 meses.</opinion>
</review>
