<?xml version="1.0" ?>
<review>
  <source value="http://www.buscape.com.br/avaliacao--deu-problema-sozinho--celular-zte-r260-desbloqueado--346259.html"/>
  <evaluation_date value="27/08/2012"/>
  <category value="Celular e Smartphone"/>
  <product value="Celular e Smartphone Celular ZTE R260 Desbloqueado"/>
  <stars value="2.0"/>
  <recommends value=""/>
  <user value="3048"/>
  <thumbsUp value="0"/>
  <thumbsDown value="0"/>
  <pros>Duração da Bateria
Operadora
</pros>
  <cons>Design
Custo-Benefício
Facilidade de Uso
Funções e Características
Durabilidade
Display
Câmera
</cons>
  <opinion>É um celular simples, tão simples que fica meio complicado navegar nas suas funções e hoje no terceiro dia que possuo ele a tela de cristal liquido já deu problema sozinha e ficou com uma parte toda preta.

O que gostei: Tem uma boa recepção de sinal.

O que não gostei: É caro pelo que oferece e deu problema sozinho, do nada.</opinion>
</review>
