<?xml version="1.0" ?>
<review>
  <source value="http://www.buscape.com.br/avaliacao--usabilidade-ruim--nokia-asha-311-desbloqueado--394315.html"/>
  <evaluation_date value="07/12/2012"/>
  <category value="Celular e Smartphone"/>
  <product value="Celular e Smartphone Nokia Asha 311 Desbloqueado"/>
  <stars value="2.0"/>
  <recommends value=""/>
  <user value="7303"/>
  <thumbsUp value="0"/>
  <thumbsDown value="0"/>
  <pros>Duração da Bateria
</pros>
  <cons>Design
Custo-Benefício
Facilidade de Uso
Funções e Características
Durabilidade
Display
Câmera
</cons>
  <opinion>O produto deveria ter sido tirado de circulação assim que detectados os problemas, não devendo ser vendido. O consumidor fica com o pepino nas mãos, mas só descobre que é ruim depois que usa.

O que gostei: Abateria dura bastante. É a única característica boa do produto.

O que não gostei: O aparelho é de difícil manuseio. O touch screen dele não obedece aos comandos. você passa muita raiva tentando abrir um único serviço, pois a tela *** de uma vez, ou para cima ou para baixo, e você não consegue ativar os aplicativos que deseja.</opinion>
</review>
