<?xml version="1.0" ?>
<review>
  <source value="http://www.buscape.com.br/avaliacao--nao-vale-a-pena-pagar-pouco--celular-motorola-w175-desbloqueado--26346.html"/>
  <evaluation_date value="08/10/2008"/>
  <category value="Celular e Smartphone"/>
  <product value="Celular e Smartphone Celular Motorola W175 Desbloqueado"/>
  <stars value="2.0"/>
  <recommends value=""/>
  <user value="22215"/>
  <thumbsUp value="6"/>
  <thumbsDown value="2"/>
  <pros>Custo-Benefício
</pros>
  <cons>Duração da Bateria
Design
Facilidade de Uso
Funções e Características
Durabilidade
Display
Operadora
</cons>
  <opinion>Celular barato, mas que não tem operacionalidade fácil.

O que gostei:  Muito barato.

O que não gostei:   Dificuldade de acesso às funções.</opinion>
</review>
