<?xml version="1.0" ?>
<review>
  <source value="http://www.buscape.com.br/avaliacao--audio-muito-ruim--celular-samsung-gt-e1182-desbloqueado--367418.html"/>
  <evaluation_date value="18/10/2012"/>
  <category value="Celular e Smartphone"/>
  <product value="Celular e Smartphone Celular Samsung GT-E1182 Desbloqueado"/>
  <stars value="2.0"/>
  <recommends value=""/>
  <user value="15926"/>
  <thumbsUp value="0"/>
  <thumbsDown value="1"/>
  <pros>Não possui nenhum ponto positivo.
</pros>
  <cons>Duração da Bateria
Design
Custo-Benefício
Facilidade de Uso
Funções e Características
Durabilidade
Display
Operadora
Câmera
</cons>
  <opinion>Já fui duas vezes na loja trocar e os dois aparelhos apresentam a mesma deficiência.

O que gostei: Aparelho leve.

O que não gostei: Audio muito ruim na emissão. A pessoa do outro lado não entende o que eu falo.</opinion>
</review>
