<?xml version="1.0" encoding="UTF-8"?>
<corpus>

	<body>
<s id="s1" ref="1" source="Running text" forest="1" text="foda deu fada fá cafu gruda flui flui flui flui debug ufo guido audi gduiogdf grande gude gduigbui guia edu adufe miudo gdfiogdfuig afgã guido guido gofe ggdfuig fui ioda gague vibratório aflui dada o que gostei ytgykljhjhggtftdrdese trará tft tft tftfrdfb tftftft te rtftftf tutti tetra te 5r 5 5e tosar w45 e str retweeet o que não gostei hjgjjhgjgh dfgdfgd grande fg fog afgã fg fog foda gado kg da fog brasília gado kg brasília gado dako dako fog fog diga di diogo ida grifa diogo diogo odbc afogada fá.">
	<graph root="s1_500">
		<terminals>
			<t id="s1_1" word="foda" lemma="foda" pos="n" morph="F S" extra="newlex"/>
			<t id="s1_2" word="deu" lemma="dar" pos="v-fin" morph="PS 3S IND VFIN" extra="nosubj nosubj nosubj nosubj nosubj nosubj nosubj nosubj nosubj nosubj nosubj nosubj nosubj nosubj nosubj nosubj nosubj nosubj nosubj nosubj nosubj nosubj nosubj nosubj cjt-head cjt-head-STA fmc mv"/>
			<t id="s1_3" word="fada" lemma="fada" pos="n" morph="F S" sem="Hmyth f-psych" extra="--"/>
			<t id="s1_4" word="fá" lemma="fá" pos="n" morph="M S" sem="ac-sign" extra="--"/>
			<t id="s1_5" word="cafu" lemma="cafu" pos="n" morph="M S" extra="heur"/>
			<t id="s1_6" word="gruda" lemma="grudar" pos="v-fin" morph="PR 3S IND VFIN" extra="nosubj nosubj cjt-STA vH fmc mv"/>
			<t id="s1_7" word="flui" lemma="fluir" pos="v-fin" morph="PR 3S IND VFIN" extra="nosubj nosubj cjt-STA vN fmc mv"/>
			<t id="s1_8" word="flui" lemma="fluir" pos="v-fin" morph="PR 3S IND VFIN" extra="nosubj nosubj cjt-STA vN fmc mv"/>
			<t id="s1_9" word="flui" lemma="fluir" pos="v-fin" morph="PR 3S IND VFIN" extra="nosubj nosubj cjt-STA vN fmc mv"/>
			<t id="s1_10" word="flui" lemma="fluir" pos="v-fin" morph="PR 3S IND VFIN" extra="nosubj nosubj cjt-STA vN fmc mv"/>
			<t id="s1_11" word="debug" lemma="debug" pos="n" morph="M S" sem="act-d" extra="--"/>
			<t id="s1_12" word="ufo" lemma="ufo" pos="n" morph="M S" sem="V" extra="--"/>
			<t id="s1_13" word="guido" lemma="guido" pos="adj" morph="M S" extra="heur np-close"/>
			<t id="s1_14" word="audi" lemma="auder" pos="v-fin" morph="PS 1S IND VFIN" extra="nosubj nosubj cjt-STA heur fmc mv"/>
			<t id="s1_15" word="gduiogdf" lemma="gduiogdf" pos="n" morph="M S" extra="foreign heur"/>
			<t id="s1_16" word="grande" lemma="grande" pos="adj" morph="M S" extra="jh"/>
			<t id="s1_17" word="gude" lemma="gude" pos="n" morph="M S" sem="game" extra="--"/>
			<t id="s1_18" word="gduigbui" lemma="gduigbuer" pos="v-fin" morph="PS 1S IND VFIN" extra="nosubj nosubj cjt-STA heur fmc mv"/>
			<t id="s1_19" word="guia" lemma="guia" pos="n" morph="F S" sem="activity" extra="--"/>
			<t id="s1_20" word="edu" lemma="edu" pos="n" morph="M S" extra="heur"/>
			<t id="s1_21" word="adufe" lemma="adufe" pos="n" morph="M S" sem="tool-mus" extra="--"/>
			<t id="s1_22" word="miudo" lemma="miúdo" pos="adj" morph="M S" extra="np-close"/>
			<t id="s1_23" word="gdfiogdfuig" lemma="gdfiogdfuig" pos="n" morph="M S" extra="foreign heur"/>
			<t id="s1_24" word="afgã" lemma="afgã" pos="n" morph="M S" extra="heur"/>
			<t id="s1_25" word="guido" lemma="guido" pos="adj" morph="M S" extra="heur np-close"/>
			<t id="s1_26" word="guido" lemma="guido" pos="adj" morph="M S" extra="heur"/>
			<t id="s1_27" word="gofe" lemma="gofe" pos="n" morph="M S" extra="heur"/>
			<t id="s1_28" word="ggdfuig" lemma="ggdfuig" pos="n" morph="M S" extra="foreign heur"/>
			<t id="s1_29" word="fui" lemma="ser" pos="v-fin" morph="PS 1S IND VFIN" extra="nosubj nosubj cjt-STA vK fmc mv"/>
			<t id="s1_30" word="ioda" lemma="iodo" pos="adj" morph="F S" extra="heur jh"/>
			<t id="s1_31" word="gague" lemma="gagar" pos="v-fin" morph="PR 1/3S SUBJ VFIN" extra="nosubj nosubj cjt-STA DERS fmc mv"/>
			<t id="s1_32" word="vibratório" lemma="vibratório" pos="adj" morph="M S" extra="nh"/>
			<t id="s1_33" word="aflui" lemma="afluir" pos="v-fin" morph="PR 3S IND VFIN" extra="nosubj nosubj cjt-STA vN fmc mv"/>
			<t id="s1_34" word="dada" lemma="dado" pos="adj" morph="F S" extra="--"/>
			<t id="s1_35" word="o_que" lemma="o_que" pos="spec" morph="M S" extra="clb rel"/>
			<t id="s1_36" word="gostei" lemma="gostar" pos="v-fin" morph="PS 1S IND VFIN" extra="nosubj nosubj cjt-STA vH mv"/>
			<t id="s1_37" word="ytgykljhjhggtftdrdese" lemma="ytgykljhjhggtftdrdese" pos="n" morph="M S" extra="heur foreign"/>
			<t id="s1_38" word="trará" lemma="trazer" pos="v-fin" morph="FUT 3S IND VFIN" extra="cjt-STA fmc mv"/>
			<t id="s1_39" word="tft" lemma="tft" pos="n" morph="M S" extra="foreign heur"/>
			<t id="s1_40" word="tft" lemma="tft" pos="n" morph="M S" extra="cjt-head cjt-head-S foreign heur"/>
			<t id="s1_41" word="tftfrdfb" lemma="tftfrdfb" pos="n" morph="M S" extra="cjt-S foreign heur"/>
			<t id="s1_42" word="tftftft" lemma="tftftft" pos="n" morph="M S" extra="cjt-S foreign heur"/>
			<t id="s1_43" word="te" lemma="tu" pos="pron-pers" morph="M/F 2S DAT" extra="refl"/>
			<t id="s1_44" word="rtftftf" lemma="rtftftf" pos="n" morph="M S" extra="cjt-S foreign heur"/>
			<t id="s1_45" word="tutti" lemma="tutter" pos="v-fin" morph="PS 1S IND VFIN" extra="nosubj nosubj cjt-STA foreign heur fmc mv"/>
			<t id="s1_46" word="tetra" lemma="tetro" pos="adj" morph="F S" extra="jh"/>
			<t id="s1_47" word="te" lemma="tu" pos="pron-pers" morph="M/F 2S DAT" extra="refl"/>
			<t id="s1_48" word="5r" lemma="5r" pos="num" morph="M/F P" extra="card"/>
			<t id="s1_49" word="5_5e" lemma="5_5e" pos="num" morph="M/F P" extra="card"/>
			<t id="s1_50" word="tosar" lemma="tosar" pos="v-inf" morph="--" extra="mv"/>
			<t id="s1_51" word="w45" lemma="w45" pos="n" morph="M S" extra="cjt-head cjt-head-Od foreign heur"/>
			<t id="s1_52" word="e" lemma="e" pos="conj-c" morph="--" extra="--"/>
			<t id="s1_53" word="str" lemma="str" pos="n" morph="M S" extra="cjt-Od foreign heur"/>
			<t id="s1_54" word="retweeet" lemma="retweeet" pos="n" morph="M S" extra="foreign heur"/>
			<t id="s1_55" word="o" lemma="o" pos="pron-dem" morph="DET M S" extra="dem"/>
			<t id="s1_56" word="que" lemma="que" pos="spec" morph="M S" extra="clb rel"/>
			<t id="s1_57" word="não" lemma="não" pos="adv" morph="--" extra="--"/>
			<t id="s1_58" word="gostei" lemma="gostar" pos="v-fin" morph="PS 1S IND VFIN" extra="cjt-STA vH mv"/>
			<t id="s1_59" word="hjgjjhgjgh" lemma="hjgjjhgjgh" pos="n" morph="M S" extra="cjt-head cjt-head-S foreign heur"/>
			<t id="s1_60" word="dfgdfgd" lemma="dfgdfgd" pos="n" morph="M S" extra="cjt-S foreign heur"/>
			<t id="s1_61" word="grande" lemma="grande" pos="adj" morph="M/F S" extra="--"/>
			<t id="s1_62" word="fg" lemma="fg" pos="n" morph="M/F S" extra="cjt-S foreign"/>
			<t id="s1_63" word="fog" lemma="fog" pos="n" morph="M S" extra="cjt-S heur"/>
			<t id="s1_64" word="afgã" lemma="afgã" pos="n" morph="M S" extra="cjt-S heur"/>
			<t id="s1_65" word="fg" lemma="fg" pos="n" morph="M/F S" extra="cjt-S foreign"/>
			<t id="s1_66" word="fog" lemma="fog" pos="n" morph="M S" extra="cjt-S heur"/>
			<t id="s1_67" word="foda" lemma="foda" pos="adj" morph="M S" extra="newlex np-close"/>
			<t id="s1_68" word="gado" lemma="gado" pos="n" morph="M S" sem="AAdom" extra="cjt-S"/>
			<t id="s1_69" word="kg" lemma="kg" pos="n" morph="M S/P" extra="cjt-S"/>
			<t id="s1_70" word="de" lemma="de" pos="prp" morph="--" extra="sam- np-close"/>
			<t id="s1_71" word="a" lemma="o" pos="art" morph="F S" extra="-sam "/>
			<t id="s1_72" word="fog" lemma="fog" pos="n" morph="F S" extra="heur"/>
			<t id="s1_73" word="brasília" lemma="brasíliar" pos="v-fin" morph="PR 3S IND VFIN" extra="cjt-STA DERS fmc mv"/>
			<t id="s1_74" word="gado" lemma="gado" pos="n" morph="M S" sem="AAdom" extra="--"/>
			<t id="s1_75" word="kg" lemma="kg" pos="n" morph="M S/P" extra="--"/>
			<t id="s1_76" word="brasília" lemma="brasíliar" pos="v-fin" morph="PR 3S IND VFIN" extra="cjt-STA DERS fmc mv"/>
			<t id="s1_77" word="gado" lemma="gado" pos="n" morph="M S" sem="AAdom" extra="--"/>
			<t id="s1_78" word="dako" lemma="dako" pos="adj" morph="M S" extra="heur foreign np-close"/>
			<t id="s1_79" word="dako" lemma="dako" pos="adj" morph="M S" extra="heur foreign"/>
			<t id="s1_80" word="fog" lemma="fog" pos="n" morph="M S" extra="cjt-head cjt-head-S heur"/>
			<t id="s1_81" word="fog" lemma="fog" pos="n" morph="M S" extra="cjt-S heur"/>
			<t id="s1_82" word="diga" lemma="dizer" pos="v-fin" morph="PR 1/3S SUBJ VFIN" extra="nosubj nosubj cjt-STA vH fmc mv"/>
			<t id="s1_83" word="di" lemma="dar" pos="v-fin" morph="PS 1S IND VFIN" extra="clb-fs mv"/>
			<t id="s1_84" word="diogo" lemma="diogo" pos="n" morph="M S" sem="Hmyth" extra="--"/>
			<t id="s1_85" word="ida" lemma="ida" pos="n" morph="F S" sem="activity act" extra="--"/>
			<t id="s1_86" word="grifa" lemma="grifo" pos="adj" morph="F S" extra="nh"/>
			<t id="s1_87" word="diogo" lemma="diogo" pos="n" morph="M S" sem="Hmyth" extra="np-close"/>
			<t id="s1_88" word="diogo" lemma="diogo" pos="n" morph="M S" sem="Hmyth" extra="np-long"/>
			<t id="s1_89" word="odbc" lemma="odbc" pos="n" morph="F S" extra="foreign heur"/>
			<t id="s1_90" word="afogada" lemma="afogar" pos="v-pcp" morph="F S" extra="--"/>
			<t id="s1_91" word="fá" lemma="fá" pos="n" morph="M S" sem="ac-sign" extra="--"/>
			<t id="s1_92" word="." lemma="--" pos="pu" morph="--" extra="--"/>
		</terminals>

		<nonterminals>
			<nt id="s1_500" cat="s">
				<edge label="STA" idref="s1_501"/>
			</nt>
			<nt id="s1_501" cat="par">
				<edge label="CJT" idref="s1_502"/>
				<edge label="CJT" idref="s1_503"/>
				<edge label="CJT" idref="s1_7"/>
				<edge label="CJT" idref="s1_8"/>
				<edge label="CJT" idref="s1_9"/>
				<edge label="CJT" idref="s1_10"/>
				<edge label="CJT" idref="s1_504"/>
				<edge label="CJT" idref="s1_506"/>
				<edge label="CJT" idref="s1_508"/>
				<edge label="CJT" idref="s1_512"/>
				<edge label="CJT" idref="s1_513"/>
				<edge label="CJT" idref="s1_514"/>
				<edge label="CJT" idref="s1_515"/>
				<edge label="CJT" idref="s1_517"/>
				<edge label="UTT" idref="s1_518"/>
				<edge label="CJT" idref="s1_521"/>
				<edge label="CJT" idref="s1_522"/>
				<edge label="CJT" idref="s1_529"/>
				<edge label="CJT" idref="s1_533"/>
				<edge label="PU" idref="s1_92"/>
			</nt>
			<nt id="s1_502" cat="fcl">
				<edge label="S" idref="s1_1"/>
				<edge label="P" idref="s1_2"/>
				<edge label="Od" idref="s1_3"/>
			</nt>
			<nt id="s1_503" cat="x">
				<edge label="fCs" idref="s1_4"/>
				<edge label="fCs" idref="s1_5"/>
				<edge label="P" idref="s1_6"/>
			</nt>
			<nt id="s1_504" cat="x">
				<edge label="fCs" idref="s1_11"/>
				<edge label="fCs" idref="s1_505"/>
				<edge label="P" idref="s1_14"/>
				<edge label="Od" idref="s1_15"/>
			</nt>
			<nt id="s1_505" cat="np">
				<edge label="H" idref="s1_12"/>
				<edge label="DN" idref="s1_13"/>
			</nt>
			<nt id="s1_506" cat="x">
				<edge label="fCs" idref="s1_507"/>
				<edge label="P" idref="s1_18"/>
				<edge label="Od" idref="s1_19"/>
			</nt>
			<nt id="s1_507" cat="np">
				<edge label="DN" idref="s1_16"/>
				<edge label="H" idref="s1_17"/>
			</nt>
			<nt id="s1_508" cat="x">
				<edge label="fCs" idref="s1_20"/>
				<edge label="fCs" idref="s1_509"/>
				<edge label="fCs" idref="s1_23"/>
				<edge label="fCs" idref="s1_510"/>
				<edge label="fCs" idref="s1_511"/>
				<edge label="fCs" idref="s1_28"/>
				<edge label="P" idref="s1_29"/>
				<edge label="Cs" idref="s1_30"/>
			</nt>
			<nt id="s1_509" cat="np">
				<edge label="H" idref="s1_21"/>
				<edge label="DN" idref="s1_22"/>
			</nt>
			<nt id="s1_510" cat="np">
				<edge label="H" idref="s1_24"/>
				<edge label="DN" idref="s1_25"/>
			</nt>
			<nt id="s1_511" cat="np">
				<edge label="DN" idref="s1_26"/>
				<edge label="H" idref="s1_27"/>
			</nt>
			<nt id="s1_512" cat="x">
				<edge label="P" idref="s1_31"/>
				<edge label="Od" idref="s1_32"/>
			</nt>
			<nt id="s1_513" cat="x">
				<edge label="P" idref="s1_33"/>
				<edge label="fCs" idref="s1_34"/>
			</nt>
			<nt id="s1_514" cat="x">
				<edge label="X" idref="s1_35"/>
				<edge label="P" idref="s1_36"/>
			</nt>
			<nt id="s1_515" cat="fcl">
				<edge label="S" idref="s1_37"/>
				<edge label="P" idref="s1_38"/>
				<edge label="Od" idref="s1_39"/>
				<edge label="S" idref="s1_516"/>
			</nt>
			<nt id="s1_516" cat="par">
				<edge label="CJT" idref="s1_40"/>
				<edge label="CJT" idref="s1_41"/>
				<edge label="CJT" idref="s1_42"/>
				<edge label="CJT" idref="s1_44"/>
			</nt>
			<nt id="s1_517" cat="x">
				<edge label="Oi" idref="s1_43"/>
				<edge label="P" idref="s1_45"/>
				<edge label="Od" idref="s1_46"/>
			</nt>
			<nt id="s1_518" cat="icl">
				<edge label="Oi" idref="s1_47"/>
				<edge label="fA" idref="s1_48"/>
				<edge label="fA" idref="s1_49"/>
				<edge label="P" idref="s1_50"/>
				<edge label="Od" idref="s1_519"/>
				<edge label="X" idref="s1_520"/>
			</nt>
			<nt id="s1_519" cat="par">
				<edge label="CJT" idref="s1_51"/>
			</nt>
			<nt id="s1_520" cat="x">
				<edge label="CO" idref="s1_52"/>
				<edge label="H" idref="s1_56"/>
			</nt>
			<nt id="s1_521" cat="fcl">
				<edge label="S" idref="s1_54"/>
			</nt>
			<nt id="s1_522" cat="fcl">
				<edge label="S" idref="s1_55"/>
				<edge label="fA" idref="s1_57"/>
				<edge label="P" idref="s1_58"/>
				<edge label="S" idref="s1_523"/>
				<edge label="P" idref="s1_73"/>
				<edge label="Od" idref="s1_74"/>
				<edge label="S" idref="s1_75"/>
			</nt>
			<nt id="s1_523" cat="par">
				<edge label="CJT" idref="s1_59"/>
				<edge label="CJT" idref="s1_60"/>
				<edge label="CJT" idref="s1_524"/>
				<edge label="CJT" idref="s1_63"/>
				<edge label="CJT" idref="s1_64"/>
				<edge label="CJT" idref="s1_65"/>
				<edge label="CJT" idref="s1_525"/>
				<edge label="CJT" idref="s1_68"/>
				<edge label="CJT" idref="s1_526"/>
			</nt>
			<nt id="s1_524" cat="np">
				<edge label="DN" idref="s1_61"/>
				<edge label="H" idref="s1_62"/>
			</nt>
			<nt id="s1_525" cat="np">
				<edge label="H" idref="s1_66"/>
				<edge label="DN" idref="s1_67"/>
			</nt>
			<nt id="s1_526" cat="np">
				<edge label="H" idref="s1_69"/>
				<edge label="DN" idref="s1_527"/>
			</nt>
			<nt id="s1_527" cat="pp">
				<edge label="H" idref="s1_70"/>
				<edge label="DP" idref="s1_528"/>
			</nt>
			<nt id="s1_528" cat="np">
				<edge label="DN" idref="s1_71"/>
				<edge label="H" idref="s1_72"/>
			</nt>
			<nt id="s1_529" cat="fcl">
				<edge label="P" idref="s1_76"/>
				<edge label="Od" idref="s1_530"/>
				<edge label="S" idref="s1_531"/>
			</nt>
			<nt id="s1_530" cat="np">
				<edge label="H" idref="s1_77"/>
				<edge label="DN" idref="s1_78"/>
			</nt>
			<nt id="s1_531" cat="par">
				<edge label="CJT" idref="s1_532"/>
				<edge label="CJT" idref="s1_81"/>
			</nt>
			<nt id="s1_532" cat="np">
				<edge label="DN" idref="s1_79"/>
				<edge label="H" idref="s1_80"/>
			</nt>
			<nt id="s1_533" cat="x">
				<edge label="P" idref="s1_82"/>
				<edge label="Od" idref="s1_534"/>
				<edge label="fCs" idref="s1_535"/>
				<edge label="fCs" idref="s1_89"/>
				<edge label="fCs" idref="s1_91"/>
			</nt>
			<nt id="s1_534" cat="fcl">
				<edge label="P" idref="s1_83"/>
				<edge label="Od" idref="s1_84"/>
			</nt>
			<nt id="s1_535" cat="np">
				<edge label="H" idref="s1_85"/>
				<edge label="fCs" idref="s1_86"/>
				<edge label="DN" idref="s1_87"/>
				<edge label="DN" idref="s1_88"/>
				<edge label="fCs" idref="s1_90"/>
			</nt>
		</nonterminals>
	</graph>
</s>

	</body>
</corpus>
